riego/__init__.py
riego/app.py
riego/boxes.py
riego/cloud.py
riego/db.py
riego/mqtt.py
riego/timer.py
riego/valves.py
riego/migrations/20210131_01_QndU0.py
riego/migrations/20210214_01_WyOHg.py
riego/migrations/20220907_01_rrOJA.py
riego/migrations/__init__.py
riego/model/__init__.py
riego/model/parameters.py
riego/ssh/known_hosts
riego/web/__init__.py
riego/web/error_pages.py
riego/web/routes.py
riego/web/security.py
riego/web/websockets.py
riego/web/static/favicon.png
riego/web/static/navbar-top-fixed.css
riego/web/static/reset.css
riego/web/static/vendor/bootstrap.bundle.min.js
riego/web/static/vendor/bootstrap.bundle.min.js.map
riego/web/static/vendor/bootstrap.min.css
riego/web/static/vendor/bootstrap.min.css.map
riego/web/templates/401.html
riego/web/templates/403.html
riego/web/templates/404.html
riego/web/templates/500.html
riego/web/templates/base.html
riego/web/templates/boxes/edit.html
riego/web/templates/boxes/index.html
riego/web/templates/boxes/new.html
riego/web/templates/boxes/view.html
riego/web/templates/dashboard/index.html
riego/web/templates/events/index.html
riego/web/templates/security/login.html
riego/web/templates/security/profile.html
riego/web/templates/system/index.html
riego/web/templates/system/parameters.html
riego/web/templates/users/edit.html
riego/web/templates/users/index.html
riego/web/templates/users/new.html
riego/web/templates/users/view.html
riego/web/templates/valves/edit.html
riego/web/templates/valves/index.html
riego/web/templates/valves/new.html
riego/web/templates/valves/view.html
riego/web/views/__init__.py
riego/web/views/boxes.py
riego/web/views/dashboard.py
riego/web/views/events.py
riego/web/views/system.py
riego/web/views/users.py
riego/web/views/valves.py
riego-0.10.3.data/scripts/setup_riego_service.sh
riego-0.10.3.dist-info/LICENSE
riego-0.10.3.dist-info/METADATA
riego-0.10.3.dist-info/WHEEL
riego-0.10.3.dist-info/entry_points.txt
riego-0.10.3.dist-info/top_level.txt
riego-0.10.3.dist-info/RECORD
